lib_cast/__init__.py
lib_cast/lib_cast.py
lib_cast/version.txt
lib_cast-0.0.3.dist-info/LICENSE
lib_cast-0.0.3.dist-info/METADATA
lib_cast-0.0.3.dist-info/WHEEL
lib_cast-0.0.3.dist-info/top_level.txt
lib_cast-0.0.3.dist-info/RECORD
